window_blinds_rpi/__init__.py
window_blinds_rpi/blinds_circuit.py
window_blinds_rpi/mcp_expander.py
window_blinds_rpi/runnable_blinds.py
window_blinds_rpi/version.py
window_blinds_rpi-0.1.0.dist-info/LICENSE
window_blinds_rpi-0.1.0.dist-info/METADATA
window_blinds_rpi-0.1.0.dist-info/WHEEL
window_blinds_rpi-0.1.0.dist-info/top_level.txt
window_blinds_rpi-0.1.0.dist-info/RECORD
