Metadata-Version: 2.1
Name: window-blinds-rpi
Version: 0.1.0
Summary: Show how to structure a Python project.
Home-page: https://github.com/tinezivic/window_blinds_rpi
Author: Tine Živič
Author-email: tine.zivic@gmail.com
License: MPL-2.0
Platform: UNKNOWN
Classifier: Development Status :: 5 - Production/Stable
Classifier: Intended Audience :: Science/Research
Classifier: Programming Language :: Python :: 2.7
Classifier: Programming Language :: Python :: 3.6
Requires-Dist: pandas
Requires-Dist: RPi.GPIO
Requires-Dist: time
Requires-Dist: asycio
